keras_eval/__init__.py
keras_eval/data_generators.py
keras_eval/eval.py
keras_eval/metrics.py
keras_eval/utils.py
keras_eval/visualizer.py
keras_eval-1.1.6.dist-info/DESCRIPTION.rst
keras_eval-1.1.6.dist-info/METADATA
keras_eval-1.1.6.dist-info/RECORD
keras_eval-1.1.6.dist-info/WHEEL
keras_eval-1.1.6.dist-info/metadata.json
keras_eval-1.1.6.dist-info/top_level.txt
