Metadata-Version: 2.0
Name: keras-eval
Version: 1.1.6
Summary: An evaluation abstraction for Keras models.
Home-page: https://www.triage.com/
Author: Triage Technologies Inc.
Author-email: ai@triage.com
License: UNKNOWN
Platform: UNKNOWN
Requires-Dist: Keras
Requires-Dist: numpy
Requires-Dist: h5py
Requires-Dist: Pillow
Requires-Dist: scipy
Requires-Dist: pandas
Requires-Dist: plotly
Requires-Dist: matplotlib
Requires-Dist: sklearn
Requires-Dist: keras-model-specs (>=0.0.30)
Requires-Dist: jupyter
